pyramid_sawing/__init__.py
pyramid_sawing/filters.py
pyramid_sawing/main.py
pyramid_sawing/tests.py
pyramid_sawing/utils.py
pyramid_sawing-1.1.3.dist-info/DESCRIPTION.rst
pyramid_sawing-1.1.3.dist-info/METADATA
pyramid_sawing-1.1.3.dist-info/RECORD
pyramid_sawing-1.1.3.dist-info/WHEEL
pyramid_sawing-1.1.3.dist-info/metadata.json
pyramid_sawing-1.1.3.dist-info/top_level.txt
