Metadata-Version: 2.0
Name: pyramid-sawing
Version: 1.1.3
Summary: Pyramid plugin for YAML logging configuration.
Home-page: https://github.com/connexions/pyramid_sawing
Author: Connexions team
Author-email: info@cnx.org
License: AGPL, See also LICENSE.txt
Platform: UNKNOWN
Requires-Dist: pyramid
Requires-Dist: PyYAML
Provides-Extra: test
Requires-Dist: mock; extra == 'test'
